{"cameraMode":{"drawMode":0,"name":"Shaded","section":"Shading Mode"},"sceneLighting":true,"audioPlay":false,"sceneViewState":{"m_AlwaysRefresh":false,"showFog":true,"showSkybox":true,"showFlares":true,"showImageEffects":true,"showParticleSystems":true,"showVisualEffectGraphs":true,"m_FxEnabled":true},"in2DMode":false,"pivot":{"x":-5.150235652923584,"y":-4.061951637268066,"z":12.557316780090332},"rotation":{"x":-0.30361008644104006,"y":0.23046259582042695,"z":-0.07593987137079239,"w":-0.9213852286338806},"size":12.847110748291016,"orthographic":false}